{"appleSKU":"","appleTeamID":"","enableCodelessAutoInitialization":true,"enableUnityGamingServicesAutoInitialization":false,"products":[{"id":"com.nplays.checkmatedking.removeads","type":1,"storeIDs":[],"defaultDescription":{"googleLocale":4,"title":"Remove Ads","description":"Do You want to remove ads ?"},"screenshotPath":"","applePriceTier":0,"googlePrice":{"data":[0,0,0,0],"num":0.0},"pricingTemplateID":"","descriptions":[],"udpPrice":{"data":[0,0,0,0],"num":0.0},"payouts":[]},{"id":"com.nplays.checkmatedking.1000Coins","type":0,"storeIDs":[],"defaultDescription":{"googleLocale":4,"title":"1000 Coins","description":"Do you want to purchase 1000 Coins ?"},"screenshotPath":"","applePriceTier":0,"googlePrice":{"data":[0,0,0,0],"num":0.0},"pricingTemplateID":"","descriptions":[],"udpPrice":{"data":[0,0,0,0],"num":0.0},"payouts":[]},{"id":"com.nplays.checkmatedking.3050Coins","type":0,"storeIDs":[],"defaultDescription":{"googleLocale":4,"title":"3050 Coins","description":"Do you want to purchase 3050 Coins ?"},"screenshotPath":"","applePriceTier":0,"googlePrice":{"data":[0,0,0,0],"num":0.0},"pricingTemplateID":"","descriptions":[],"udpPrice":{"data":[0,0,0,0],"num":0.0},"payouts":[]},{"id":"com.nplays.checkmatedking.7000Coins","type":0,"storeIDs":[],"defaultDescription":{"googleLocale":4,"title":"7000 Coins","description":"Do you want to purchase 7000 Coins ?"},"screenshotPath":"","applePriceTier":0,"googlePrice":{"data":[0,0,0,0],"num":0.0},"pricingTemplateID":"","descriptions":[],"udpPrice":{"data":[0,0,0,0],"num":0.0},"payouts":[]},{"id":"com.nplays.checkmatedking.15000Coins","type":0,"storeIDs":[],"defaultDescription":{"googleLocale":4,"title":"15000 Coins","description":"Do you want to purchase 15000 Coins ?"},"screenshotPath":"","applePriceTier":0,"googlePrice":{"data":[0,0,0,0],"num":0.0},"pricingTemplateID":"","descriptions":[],"udpPrice":{"data":[0,0,0,0],"num":0.0},"payouts":[]}]}